bike_rental_model/__init__.py
bike_rental_model/pipeline.py
bike_rental_model/predict.py
bike_rental_model/train_pipeline.py
bike_rental_package-1.0.0.dist-info/METADATA
bike_rental_package-1.0.0.dist-info/WHEEL
bike_rental_package-1.0.0.dist-info/top_level.txt
bike_rental_package-1.0.0.dist-info/RECORD
