Metadata-Version: 2.1
Name: bike-rental-package
Version: 1.0.0
Summary: IISc Projects
Author: IISc Team 5 Group
Author-email: manikandan_np@yahoo.com
Requires-Dist: numpy (<2.0.0,>=1.21.0)
Requires-Dist: pandas (<2.0.0,>=1.3.5)
Requires-Dist: pydantic (<2.0.0,>=1.8.1)
Requires-Dist: scikit-learn (<2.0.0,>=1.1.3)
Requires-Dist: strictyaml (<2.0.0,>=1.3.2)
Requires-Dist: ruamel.yaml (<1.0.0,>=0.16.12)
Requires-Dist: joblib (<2.0.0,>=1.0.1)
